odoo/addons/l10n_es_sigaus_sale/README.rst
odoo/addons/l10n_es_sigaus_sale/__init__.py
odoo/addons/l10n_es_sigaus_sale/__manifest__.py
odoo/addons/l10n_es_sigaus_sale/hooks.py
odoo/addons/l10n_es_sigaus_sale/data/exception_templates.xml
odoo/addons/l10n_es_sigaus_sale/i18n/ca.po
odoo/addons/l10n_es_sigaus_sale/i18n/es.po
odoo/addons/l10n_es_sigaus_sale/i18n/l10n_es_sigaus_sale.pot
odoo/addons/l10n_es_sigaus_sale/models/__init__.py
odoo/addons/l10n_es_sigaus_sale/models/account_move.py
odoo/addons/l10n_es_sigaus_sale/models/sale_order.py
odoo/addons/l10n_es_sigaus_sale/models/sale_order_line.py
odoo/addons/l10n_es_sigaus_sale/readme/CONFIGURE.rst
odoo/addons/l10n_es_sigaus_sale/readme/CONTRIBUTORS.rst
odoo/addons/l10n_es_sigaus_sale/readme/DESCRIPTION.rst
odoo/addons/l10n_es_sigaus_sale/readme/ROADMAP.rst
odoo/addons/l10n_es_sigaus_sale/readme/USAGE.rst
odoo/addons/l10n_es_sigaus_sale/report/ir_actions_report_templates.xml
odoo/addons/l10n_es_sigaus_sale/static/description/icon.png
odoo/addons/l10n_es_sigaus_sale/static/description/icon.svg
odoo/addons/l10n_es_sigaus_sale/static/description/index.html
odoo/addons/l10n_es_sigaus_sale/tests/__init__.py
odoo/addons/l10n_es_sigaus_sale/tests/test_l10n_es_sigaus_sale.py
odoo/addons/l10n_es_sigaus_sale/views/sale_order_views.xml
odoo_addon_l10n_es_sigaus_sale-16.0.1.0.3.dist-info/METADATA
odoo_addon_l10n_es_sigaus_sale-16.0.1.0.3.dist-info/WHEEL
odoo_addon_l10n_es_sigaus_sale-16.0.1.0.3.dist-info/top_level.txt
odoo_addon_l10n_es_sigaus_sale-16.0.1.0.3.dist-info/RECORD
