Metadata-Version: 2.1
Name: odoo-addon-l10n_es_sigaus_sale
Version: 16.0.1.0.3
Summary: Sist. gestión aceites industriales usados en España - Ventas
Home-page: https://github.com/OCA/l10n-spain
Author: Sygel, Odoo Community Association (OCA)
Author-email: support@odoo-community.org
License: AGPL-3
Classifier: Programming Language :: Python
Classifier: Framework :: Odoo
Classifier: Framework :: Odoo :: 16.0
Classifier: License :: OSI Approved :: GNU Affero General Public License v3
Requires-Python: >=3.10
Requires-Dist: odoo-addon-l10n-es-sigaus-account<16.1dev,>=16.0dev
Requires-Dist: odoo<16.1dev,>=16.0a
